ntsbuildtools/__init__.py
ntsbuildtools/exceptions.py
ntsbuildtools/io.py
ntsbuildtools/main.py
ntsbuildtools/util.py
ntsbuildtools/ansible/__init__.py
ntsbuildtools/ansible/inventory.py
ntsbuildtools/ansible/playbook/__init__.py
ntsbuildtools/ansible/playbook/results.py
ntsbuildtools/ansible/return_values/__init__.py
ntsbuildtools/ansible/return_values/default.py
ntsbuildtools/ansible/return_values/factory.py
ntsbuildtools/ansible/return_values/junos_config.py
ntsbuildtools/cli/__init__.py
ntsbuildtools/cli/framework.py
ntsbuildtools/cli/tree.py
ntsbuildtools/markdown/__init__.py
ntsbuildtools/markdown/comments.py
ntsbuildtools/subcommands/__init__.py
ntsbuildtools/subcommands/example/__init__.py
ntsbuildtools/subcommands/example/hello_world.py
ntsbuildtools/subcommands/infer/__init__.py
ntsbuildtools/subcommands/infer/ansible/__init__.py
ntsbuildtools/subcommands/infer/ansible/playbook_limit.py
ntsbuildtools/subcommands/parse/__init__.py
ntsbuildtools/subcommands/parse/ansible/__init__.py
ntsbuildtools/subcommands/parse/ansible/json.py
ntsbuildtools/subcommands/post/__init__.py
ntsbuildtools/subcommands/post/bitbucket/__init__.py
ntsbuildtools/subcommands/post/bitbucket/build_status.py
ntsbuildtools/subcommands/post/bitbucket/pr_comment.py
ntsbuildtools/subcommands/post/bitbucket/pull_request.py
ntsbuildtools/subcommands/post/github/__init__.py
ntsbuildtools/subcommands/post/github/pr_comment.py
ntsbuildtools/subcommands/post/teams/__init__.py
ntsbuildtools/subcommands/post/teams/card.py
ntsbuildtools/teams/__init__.py
ntsbuildtools/teams/card_template.py
ntsbuildtools/teams/cards.py
ntsbuildtools-4.0.11.dist-info/METADATA
ntsbuildtools-4.0.11.dist-info/WHEEL
ntsbuildtools-4.0.11.dist-info/entry_points.txt
ntsbuildtools-4.0.11.dist-info/top_level.txt
ntsbuildtools-4.0.11.dist-info/RECORD
