Metadata-Version: 2.1
Name: ntsbuildtools
Version: 4.0.11
Summary: CLI toolset that supports CICD processes.
Home-page: https://git.uoregon.edu/projects/ISN/repos/buildtools/browse
Author: Network & Telecom Svcs (University of Oregon)
Author-email: rleonar7@uoregon.edu
License: MIT
Keywords: Jenkins,NTS,UO,CLI,Integrations,API
Classifier: Development Status :: 3 - Alpha
Classifier: Intended Audience :: Developers
Classifier: Topic :: Software Development :: Build Tools
Classifier: License :: OSI Approved :: MIT License
Classifier: Programming Language :: Python :: 3.8
Requires-Dist: requests >=2.0
Requires-Dist: ansible >=2
Requires-Dist: ConfigArgParse >=1.0
Requires-Dist: anytree >=2.0
Requires-Dist: art >=2.0
Requires-Dist: mdfrag >=0.1.0
